tindi/__init__.py
tindi/calculadora.py
tindi-0.0.1.dist-info/LICENSE.txt
tindi-0.0.1.dist-info/METADATA
tindi-0.0.1.dist-info/WHEEL
tindi-0.0.1.dist-info/top_level.txt
tindi-0.0.1.dist-info/RECORD
